braze_mcp/__init__.py
braze_mcp/main.py
braze_mcp/registry_builder.py
braze_mcp/server.py
braze_mcp/models/__init__.py
braze_mcp/models/campaign_dataseries.py
braze_mcp/models/campaigns.py
braze_mcp/models/canvas_dataseries.py
braze_mcp/models/canvases.py
braze_mcp/models/catalogs.py
braze_mcp/models/common.py
braze_mcp/models/custom_attributes.py
braze_mcp/models/errors.py
braze_mcp/models/events.py
braze_mcp/models/integrations.py
braze_mcp/models/kpi.py
braze_mcp/models/message_statistics.py
braze_mcp/models/messages.py
braze_mcp/models/preference_centers.py
braze_mcp/models/purchases.py
braze_mcp/models/sdk_authentication.py
braze_mcp/models/segments.py
braze_mcp/models/send_dataseries.py
braze_mcp/models/sessions.py
braze_mcp/models/subscription_groups.py
braze_mcp/models/templates.py
braze_mcp/prompts/__init__.py
braze_mcp/prompts/campaigns.py
braze_mcp/tools/__init__.py
braze_mcp/tools/campaigns.py
braze_mcp/tools/canvases.py
braze_mcp/tools/catalogs.py
braze_mcp/tools/custom_attributes.py
braze_mcp/tools/events.py
braze_mcp/tools/integrations.py
braze_mcp/tools/kpi.py
braze_mcp/tools/messages.py
braze_mcp/tools/preference_centers.py
braze_mcp/tools/purchases.py
braze_mcp/tools/sdk_authentication.py
braze_mcp/tools/segments.py
braze_mcp/tools/sends.py
braze_mcp/tools/sessions.py
braze_mcp/tools/subscription_groups.py
braze_mcp/tools/templates.py
braze_mcp/utils/__init__.py
braze_mcp/utils/context.py
braze_mcp/utils/http.py
braze_mcp/utils/logging.py
braze_mcp_server-1.0.4.dist-info/METADATA
braze_mcp_server-1.0.4.dist-info/WHEEL
braze_mcp_server-1.0.4.dist-info/entry_points.txt
braze_mcp_server-1.0.4.dist-info/RECORD
