Metadata-Version: 2.4
Name: braze-mcp-server
Version: 1.0.4
Summary: Braze MCP Server - Model Context Protocol server for Braze REST API Read-Only access
Author-email: McKay Harris <mckay.harris@braze.com>, Mohammad Atallah <M.Atallah@braze.com>
License: MIT
Keywords: ai,api,automation,braze,marketing,mcp,model-context-protocol
Classifier: Development Status :: 4 - Beta
Classifier: Intended Audience :: Developers
Classifier: License :: OSI Approved :: MIT License
Classifier: Programming Language :: Python :: 3
Classifier: Programming Language :: Python :: 3.12
Classifier: Topic :: Internet :: WWW/HTTP :: HTTP Servers
Classifier: Topic :: Scientific/Engineering :: Artificial Intelligence
Classifier: Topic :: Software Development :: Libraries :: Python Modules
Requires-Python: >=3.12
Requires-Dist: fastapi[standard]>=0.116.1
Requires-Dist: httpx>=0.28.1
Requires-Dist: mcp[cli]>=1.11.0
Requires-Dist: python-dotenv>=1.1.1
Provides-Extra: dev
Requires-Dist: bandit>=1.8.6; extra == 'dev'
Requires-Dist: mypy>=1.17.0; extra == 'dev'
Requires-Dist: pytest-asyncio>=1.1.0; extra == 'dev'
Requires-Dist: pytest-cov>=6.2.1; extra == 'dev'
Requires-Dist: pytest>=8.4.1; extra == 'dev'
Requires-Dist: ruff>=0.12.3; extra == 'dev'
Requires-Dist: twine>=5.0.0; extra == 'dev'
